hoppr_security_commons/README.md
hoppr_security_commons/__init__.py
hoppr_security_commons/py.typed
hoppr_security_commons/reporting/__init__.py
hoppr_security_commons/reporting/models.py
hoppr_security_commons/reporting/py.typed
hoppr_security_commons/reporting/reporting.py
hoppr_security_commons/reporting/templates/assets/vulnerabilities.css
hoppr_security_commons/reporting/templates/package-lock.json
hoppr_security_commons/reporting/templates/package.json
hoppr_security_commons/reporting/templates/tailwind.config.js
hoppr_security_commons/reporting/templates/vulnerabilities.html
hoppr_security_commons/reporting/templates/vulnerability.css
hoppr_security_commons/reporting/templates/vulnerability_details.html
hoppr_security_commons/utils.py
hoppr_security_commons/vulnerability_combiner.py
hoppr_security_commons/vulnerability_scanner.py
security_commons/__init__.py
hoppr_security_commons-0.0.114.dist-info/LICENSE.md
hoppr_security_commons-0.0.114.dist-info/METADATA
hoppr_security_commons-0.0.114.dist-info/WHEEL
hoppr_security_commons-0.0.114.dist-info/RECORD
