Metadata-Version: 2.1
Name: hoppr-security-commons
Version: 0.0.114
Summary: Common Library For hoppr-cop
License: MIT
Author: kganger
Author-email: keith.e.ganger@lmco.com
Requires-Python: >=3.10,<4.0
Classifier: License :: OSI Approved :: MIT License
Classifier: Programming Language :: Python :: 3
Classifier: Programming Language :: Python :: 3.10
Classifier: Programming Language :: Python :: 3.11
Classifier: Programming Language :: Python :: 3.12
Classifier: Programming Language :: Python :: 3.13
Requires-Dist: hoppr-cyclonedx-models (==0.*)
Requires-Dist: jinja2 (>=3.1.2,<4.0.0)
Requires-Dist: packageurl-python (==0.*)
Requires-Dist: requests (>=2.29.0,<3.0.0)
Requires-Dist: tabulate (==0.*)
Requires-Dist: typer (==0.*)
